chat_webhooks/__init__.py
chat_webhooks/__main__.py
chat_webhooks/core.py
chat_webhooks/errors.py
chat_webhooks-1.0.1.dist-info/LICENSE
chat_webhooks-1.0.1.dist-info/WHEEL
chat_webhooks-1.0.1.dist-info/METADATA
chat_webhooks-1.0.1.dist-info/RECORD
